setup.py
chinup/__init__.py
chinup/allauth.py
chinup/cache.py
chinup/chinup.py
chinup/exceptions.py
chinup/lowlevel.py
chinup/middleware.py
chinup/queue.py
chinup/settings.py
chinup/testing.py
chinup/util.py
chinup.egg-info/PKG-INFO
chinup.egg-info/SOURCES.txt
chinup.egg-info/dependency_links.txt
chinup.egg-info/requires.txt
chinup.egg-info/top_level.txt