Metadata-Version: 1.0
Name: chinup
Version: 0.3.2
Summary: Python Facebook Graph API client
Home-page: https://github.com/pagepart/chinup
Author: PagePart Team
Author-email: opensource@pagepart.com
License: MIT
Platform: UNKNOWN
